toller/__init__.py
toller/breakers.py
toller/decorators.py
toller/exceptions.py
toller/limiters.py
toller/retry.py
toller-0.0.3.dist-info/METADATA
toller-0.0.3.dist-info/WHEEL
toller-0.0.3.dist-info/licenses/LICENSE
toller-0.0.3.dist-info/RECORD
