Metadata-Version: 2.4
Name: toller
Version: 0.0.3
Summary: Intelligent async flow controller for Python - making complex asyncio workflows manageable
Project-URL: Homepage, https://github.com/NolanTrem/toller
Project-URL: Issues, https://github.com/NolanTrem/toller/issues
Project-URL: Documentation, https://tollerlib.dev
Author-email: Nolan Tremelling <nolantremelling@gmail.com>
License: MIT License
License-File: LICENSE
Keywords: ai-workflows,async,async-workflows,asyncio,concurrency,flow-control,rate-limiting
Classifier: Development Status :: 3 - Alpha
Classifier: Intended Audience :: Developers
Classifier: License :: OSI Approved :: MIT License
Classifier: Programming Language :: Python :: 3
Classifier: Programming Language :: Python :: 3.10
Classifier: Programming Language :: Python :: 3.11
Classifier: Programming Language :: Python :: 3.12
Classifier: Programming Language :: Python :: 3.13
Classifier: Topic :: Software Development :: Libraries :: Python Modules
Requires-Python: >=3.10
Provides-Extra: dev
Requires-Dist: black>=23.0.0; extra == 'dev'
Requires-Dist: isort>=5.12.0; extra == 'dev'
Requires-Dist: mypy>=1.0.0; extra == 'dev'
Requires-Dist: pytest-asyncio>=0.20.0; extra == 'dev'
Requires-Dist: pytest>=7.0.0; extra == 'dev'
Requires-Dist: ruff>=0.0.200; extra == 'dev'
Provides-Extra: docs
Requires-Dist: myst-parser>=1.0.0; extra == 'docs'
Requires-Dist: sphinx-rtd-theme>=1.2.0; extra == 'docs'
Requires-Dist: sphinx>=6.0.0; extra == 'docs'
